airtable_export/__init__.py
airtable_export/cli.py
airtable_export-0.7.1.dist-info/LICENSE
airtable_export-0.7.1.dist-info/METADATA
airtable_export-0.7.1.dist-info/WHEEL
airtable_export-0.7.1.dist-info/entry_points.txt
airtable_export-0.7.1.dist-info/top_level.txt
airtable_export-0.7.1.dist-info/RECORD
