Metadata-Version: 2.1
Name: airtable-export
Version: 0.7.1
Summary: Export Airtable data to files on disk
Home-page: https://github.com/simonw/airtable-export
Author: Simon Willison
License: Apache License, Version 2.0
Project-URL: Issues, https://github.com/simonw/airtable-export/issues
Project-URL: CI, https://github.com/simonw/airtable-export/actions
Project-URL: Changelog, https://github.com/simonw/airtable-export/releases
Platform: UNKNOWN
Provides-Extra: test
